{
  "__inputs": [
    {
      "name": "DS_PROMETHEUS",
      "label": "prometheus",
      "description": "",
      "type": "datasource",
      "pluginId": "prometheus",
      "pluginName": "Prometheus"
    }
  ],
  "__elements": {},
  "__requires": [
    {
      "type": "grafana",
      "id": "grafana",
      "name": "Grafana",
      "version": "11.1.4"
    },
    {
      "type": "datasource",
      "id": "prometheus",
      "name": "Prometheus",
      "version": "1.0.0"
    },
    {
      "type": "panel",
      "id": "table",
      "name": "Table",
      "version": ""
    },
    {
      "type": "panel",
      "id": "timeseries",
      "name": "Time series",
      "version": ""
    }
  ],
  "annotations": {
    "list": [
      {
        "builtIn": 1,
        "datasource": {
          "type": "grafana",
          "uid": "-- Grafana --"
        },
        "enable": true,
        "hide": true,
        "iconColor": "rgba(0, 211, 255, 1)",
        "name": "Annotations & Alerts",
        "type": "dashboard"
      }
    ]
  },
  "description": "grafana v11.x 版本上的更新。",
  "editable": true,
  "fiscalYearStartMonth": 0,
  "graphTooltip": 0,
  "id": null,
  "links": [],
  "panels": [
    {
      "collapsed": false,
      "gridPos": {
        "h": 1,
        "w": 24,
        "x": 0,
        "y": 0
      },
      "id": 2,
      "panels": [],
      "title": "CPU/MEM",
      "type": "row"
    },
    {
      "datasource": {
        "type": "prometheus",
        "uid": "${datasource}"
      },
      "fieldConfig": {
        "defaults": {
          "color": {
            "mode": "palette-classic"
          },
          "custom": {
            "axisBorderShow": false,
            "axisCenteredZero": false,
            "axisColorMode": "text",
            "axisLabel": "",
            "axisPlacement": "auto",
            "barAlignment": 0,
            "drawStyle": "line",
            "fillOpacity": 0,
            "gradientMode": "none",
            "hideFrom": {
              "legend": false,
              "tooltip": false,
              "viz": false
            },
            "insertNulls": false,
            "lineInterpolation": "linear",
            "lineWidth": 1,
            "pointSize": 5,
            "scaleDistribution": {
              "type": "linear"
            },
            "showPoints": "auto",
            "spanNulls": false,
            "stacking": {
              "group": "A",
              "mode": "none"
            },
            "thresholdsStyle": {
              "mode": "off"
            }
          },
          "mappings": [],
          "thresholds": {
            "mode": "absolute",
            "steps": [
              {
                "color": "green",
                "value": null
              },
              {
                "color": "red",
                "value": 80
              }
            ]
          },
          "unit": "percentunit"
        },
        "overrides": []
      },
      "gridPos": {
        "h": 16,
        "w": 24,
        "x": 0,
        "y": 1
      },
      "id": 1,
      "options": {
        "legend": {
          "calcs": [
            "max",
            "mean",
            "last"
          ],
          "displayMode": "table",
          "placement": "right",
          "showLegend": true
        },
        "tooltip": {
          "mode": "single",
          "sort": "none"
        }
      },
      "targets": [
        {
          "datasource": {
            "type": "prometheus",
            "uid": "${DS_PROMETHEUS}"
          },
          "editorMode": "code",
          "expr": "(1 - avg(irate(node_cpu_seconds_total{mode=\"idle\", job=\"$job\"}[1m])) by(instance))",
          "instant": false,
          "legendFormat": "__auto",
          "range": true,
          "refId": "A"
        }
      ],
      "title": "CPU%",
      "type": "timeseries"
    },
    {
      "datasource": {
        "type": "prometheus",
        "uid": "${datasource}"
      },
      "fieldConfig": {
        "defaults": {
          "color": {
            "mode": "palette-classic"
          },
          "custom": {
            "axisBorderShow": false,
            "axisCenteredZero": false,
            "axisColorMode": "text",
            "axisLabel": "",
            "axisPlacement": "auto",
            "barAlignment": 0,
            "drawStyle": "line",
            "fillOpacity": 0,
            "gradientMode": "none",
            "hideFrom": {
              "legend": false,
              "tooltip": false,
              "viz": false
            },
            "insertNulls": false,
            "lineInterpolation": "linear",
            "lineWidth": 1,
            "pointSize": 5,
            "scaleDistribution": {
              "type": "linear"
            },
            "showPoints": "auto",
            "spanNulls": false,
            "stacking": {
              "group": "A",
              "mode": "none"
            },
            "thresholdsStyle": {
              "mode": "off"
            }
          },
          "mappings": [],
          "thresholds": {
            "mode": "absolute",
            "steps": [
              {
                "color": "green",
                "value": null
              },
              {
                "color": "red",
                "value": 80
              }
            ]
          },
          "unit": "percentunit"
        },
        "overrides": []
      },
      "gridPos": {
        "h": 12,
        "w": 15,
        "x": 0,
        "y": 17
      },
      "id": 3,
      "options": {
        "legend": {
          "calcs": [
            "last"
          ],
          "displayMode": "table",
          "placement": "right",
          "showLegend": true
        },
        "tooltip": {
          "mode": "single",
          "sort": "none"
        }
      },
      "targets": [
        {
          "datasource": {
            "type": "prometheus",
            "uid": "${DS_PROMETHEUS}"
          },
          "editorMode": "code",
          "expr": "(1 - (node_memory_MemAvailable_bytes / node_memory_MemTotal_bytes))",
          "instant": false,
          "legendFormat": "{{instance}}",
          "range": true,
          "refId": "A"
        }
      ],
      "title": "MEM",
      "type": "timeseries"
    },
    {
      "datasource": {
        "type": "prometheus",
        "uid": "${datasource}"
      },
      "description": "",
      "fieldConfig": {
        "defaults": {
          "color": {
            "mode": "thresholds"
          },
          "custom": {
            "align": "left",
            "cellOptions": {
              "type": "auto"
            },
            "inspect": false
          },
          "mappings": [],
          "thresholds": {
            "mode": "absolute",
            "steps": [
              {
                "color": "green",
                "value": null
              },
              {
                "color": "red",
                "value": 80
              }
            ]
          },
          "unit": "bytes"
        },
        "overrides": []
      },
      "gridPos": {
        "h": 12,
        "w": 9,
        "x": 15,
        "y": 17
      },
      "id": 5,
      "options": {
        "cellHeight": "sm",
        "footer": {
          "countRows": false,
          "fields": "",
          "reducer": [
            "sum"
          ],
          "show": false
        },
        "showHeader": true
      },
      "pluginVersion": "11.1.4",
      "targets": [
        {
          "datasource": {
            "type": "prometheus",
            "uid": "${DS_PROMETHEUS}"
          },
          "editorMode": "code",
          "exemplar": false,
          "expr": "node_memory_MemTotal_bytes{job=\"$job\"}",
          "format": "table",
          "instant": true,
          "interval": "",
          "legendFormat": "__auto",
          "range": false,
          "refId": "A"
        },
        {
          "datasource": {
            "type": "prometheus",
            "uid": "${datasource}"
          },
          "editorMode": "code",
          "exemplar": false,
          "expr": "node_uname_info{job=\"$job\"}",
          "format": "table",
          "hide": false,
          "instant": true,
          "interval": "",
          "legendFormat": "__auto",
          "range": false,
          "refId": "B"
        }
      ],
      "title": "MEM-总量",
      "transformations": [
        {
          "id": "filterFieldsByName",
          "options": {
            "include": {
              "names": [
                "instance",
                "Value #A",
                "nodename"
              ]
            }
          }
        },
        {
          "id": "merge",
          "options": {}
        },
        {
          "id": "organize",
          "options": {
            "excludeByName": {},
            "includeByName": {},
            "indexByName": {
              "Value #A": 2,
              "instance": 0,
              "nodename": 1
            },
            "renameByName": {
              "Value #A": "MEM总量",
              "nodename": "hostname"
            }
          }
        }
      ],
      "type": "table"
    },
    {
      "datasource": {
        "type": "prometheus",
        "uid": "${DS_PROMETHEUS}"
      },
      "fieldConfig": {
        "defaults": {
          "color": {
            "mode": "palette-classic"
          },
          "custom": {
            "axisBorderShow": false,
            "axisCenteredZero": false,
            "axisColorMode": "text",
            "axisLabel": "",
            "axisPlacement": "auto",
            "barAlignment": 0,
            "drawStyle": "line",
            "fillOpacity": 0,
            "gradientMode": "none",
            "hideFrom": {
              "legend": false,
              "tooltip": false,
              "viz": false
            },
            "insertNulls": false,
            "lineInterpolation": "linear",
            "lineWidth": 1,
            "pointSize": 5,
            "scaleDistribution": {
              "type": "linear"
            },
            "showPoints": "auto",
            "spanNulls": false,
            "stacking": {
              "group": "A",
              "mode": "none"
            },
            "thresholdsStyle": {
              "mode": "off"
            }
          },
          "mappings": [],
          "thresholds": {
            "mode": "absolute",
            "steps": [
              {
                "color": "green"
              },
              {
                "color": "red",
                "value": 80
              }
            ]
          },
          "unit": "percent"
        },
        "overrides": []
      },
      "gridPos": {
        "h": 12,
        "w": 15,
        "x": 0,
        "y": 29
      },
      "id": 4,
      "options": {
        "legend": {
          "calcs": [
            "lastNotNull"
          ],
          "displayMode": "table",
          "placement": "right",
          "showLegend": true
        },
        "tooltip": {
          "mode": "single",
          "sort": "none"
        }
      },
      "targets": [
        {
          "datasource": {
            "type": "prometheus",
            "uid": "${DS_PROMETHEUS}"
          },
          "editorMode": "code",
          "expr": "(1 - (node_memory_SwapFree_bytes / node_memory_SwapTotal_bytes)) * 100",
          "instant": false,
          "legendFormat": "{{instance}}",
          "range": true,
          "refId": "A"
        }
      ],
      "title": "SWAP",
      "type": "timeseries"
    },
    {
      "datasource": {
        "type": "prometheus",
        "uid": "${DS_PROMETHEUS}"
      },
      "fieldConfig": {
        "defaults": {
          "color": {
            "mode": "thresholds"
          },
          "custom": {
            "align": "left",
            "cellOptions": {
              "type": "auto"
            },
            "inspect": false
          },
          "mappings": [],
          "thresholds": {
            "mode": "absolute",
            "steps": [
              {
                "color": "green"
              },
              {
                "color": "red",
                "value": 80
              }
            ]
          },
          "unit": "bytes"
        },
        "overrides": []
      },
      "gridPos": {
        "h": 12,
        "w": 9,
        "x": 15,
        "y": 29
      },
      "id": 6,
      "options": {
        "cellHeight": "sm",
        "footer": {
          "countRows": false,
          "fields": "",
          "reducer": [
            "sum"
          ],
          "show": false
        },
        "showHeader": true
      },
      "pluginVersion": "11.1.4",
      "targets": [
        {
          "datasource": {
            "type": "prometheus",
            "uid": "${DS_PROMETHEUS}"
          },
          "editorMode": "code",
          "exemplar": false,
          "expr": "node_memory_SwapTotal_bytes{job=\"$job\"}",
          "format": "table",
          "instant": true,
          "interval": "",
          "legendFormat": "__auto",
          "range": false,
          "refId": "A"
        },
        {
          "datasource": {
            "type": "prometheus",
            "uid": "${DS_PROMETHEUS}"
          },
          "editorMode": "code",
          "exemplar": false,
          "expr": "node_uname_info{job=\"$job\"}",
          "format": "table",
          "hide": false,
          "instant": true,
          "legendFormat": "__auto",
          "range": false,
          "refId": "B"
        }
      ],
      "title": "SWAP总量",
      "transformations": [
        {
          "id": "filterFieldsByName",
          "options": {
            "include": {
              "names": [
                "instance",
                "Value #A",
                "machine",
                "nodename",
                "release"
              ]
            }
          }
        },
        {
          "id": "merge",
          "options": {}
        },
        {
          "id": "organize",
          "options": {
            "excludeByName": {},
            "includeByName": {},
            "indexByName": {
              "Value #A": 2,
              "Value #B": 5,
              "instance": 0,
              "machine": 3,
              "nodename": 1,
              "release": 4
            },
            "renameByName": {
              "Value #A": "SWAP总量",
              "nodename": "hostname"
            }
          }
        }
      ],
      "type": "table"
    },
    {
      "collapsed": true,
      "gridPos": {
        "h": 1,
        "w": 24,
        "x": 0,
        "y": 41
      },
      "id": 7,
      "panels": [
        {
          "datasource": {
            "type": "prometheus",
            "uid": "${datasource}"
          },
          "fieldConfig": {
            "defaults": {
              "color": {
                "mode": "palette-classic"
              },
              "custom": {
                "axisBorderShow": false,
                "axisCenteredZero": false,
                "axisColorMode": "text",
                "axisLabel": "",
                "axisPlacement": "auto",
                "barAlignment": 0,
                "drawStyle": "line",
                "fillOpacity": 0,
                "gradientMode": "none",
                "hideFrom": {
                  "legend": false,
                  "tooltip": false,
                  "viz": false
                },
                "insertNulls": false,
                "lineInterpolation": "linear",
                "lineWidth": 1,
                "pointSize": 5,
                "scaleDistribution": {
                  "type": "linear"
                },
                "showPoints": "auto",
                "spanNulls": false,
                "stacking": {
                  "group": "A",
                  "mode": "none"
                },
                "thresholdsStyle": {
                  "mode": "off"
                }
              },
              "mappings": [],
              "thresholds": {
                "mode": "absolute",
                "steps": [
                  {
                    "color": "green"
                  },
                  {
                    "color": "red",
                    "value": 80
                  }
                ]
              },
              "unit": "percent"
            },
            "overrides": []
          },
          "gridPos": {
            "h": 13,
            "w": 24,
            "x": 0,
            "y": 42
          },
          "id": 8,
          "options": {
            "legend": {
              "calcs": [
                "max",
                "mean",
                "last"
              ],
              "displayMode": "table",
              "placement": "right",
              "showLegend": true
            },
            "tooltip": {
              "mode": "single",
              "sort": "none"
            }
          },
          "targets": [
            {
              "datasource": {
                "type": "prometheus",
                "uid": "${DS_PROMETHEUS}"
              },
              "editorMode": "code",
              "expr": "gpu_nvidia_usage{exported_job=\"$gpu_nvidia\"}",
              "instant": false,
              "legendFormat": "{{instance}}",
              "range": true,
              "refId": "A"
            }
          ],
          "title": "GPU%",
          "type": "timeseries"
        },
        {
          "datasource": {
            "type": "prometheus",
            "uid": "${datasource}"
          },
          "fieldConfig": {
            "defaults": {
              "color": {
                "mode": "palette-classic"
              },
              "custom": {
                "axisBorderShow": false,
                "axisCenteredZero": false,
                "axisColorMode": "text",
                "axisLabel": "",
                "axisPlacement": "auto",
                "barAlignment": 0,
                "drawStyle": "line",
                "fillOpacity": 0,
                "gradientMode": "none",
                "hideFrom": {
                  "legend": false,
                  "tooltip": false,
                  "viz": false
                },
                "insertNulls": false,
                "lineInterpolation": "linear",
                "lineWidth": 1,
                "pointSize": 5,
                "scaleDistribution": {
                  "type": "linear"
                },
                "showPoints": "auto",
                "spanNulls": false,
                "stacking": {
                  "group": "A",
                  "mode": "none"
                },
                "thresholdsStyle": {
                  "mode": "off"
                }
              },
              "mappings": [],
              "thresholds": {
                "mode": "absolute",
                "steps": [
                  {
                    "color": "green"
                  },
                  {
                    "color": "red",
                    "value": 80
                  }
                ]
              },
              "unit": "percent"
            },
            "overrides": []
          },
          "gridPos": {
            "h": 11,
            "w": 15,
            "x": 0,
            "y": 55
          },
          "id": 9,
          "options": {
            "legend": {
              "calcs": [
                "max",
                "mean",
                "lastNotNull"
              ],
              "displayMode": "table",
              "placement": "right",
              "showLegend": true
            },
            "tooltip": {
              "mode": "single",
              "sort": "none"
            }
          },
          "targets": [
            {
              "datasource": {
                "type": "prometheus",
                "uid": "${DS_PROMETHEUS}"
              },
              "editorMode": "code",
              "expr": "(gpu_nvidia_memory_usage{exported_job=\"$gpu_nvidia\"} / gpu_nvidia_memory_total{exported_job=\"$gpu_nvidia\"}) * 100",
              "instant": false,
              "legendFormat": "{{instance}}",
              "range": true,
              "refId": "A"
            }
          ],
          "title": "GPU MEM%",
          "type": "timeseries"
        },
        {
          "datasource": {
            "type": "prometheus",
            "uid": "${datasource}"
          },
          "fieldConfig": {
            "defaults": {
              "color": {
                "mode": "thresholds"
              },
              "custom": {
                "align": "left",
                "cellOptions": {
                  "type": "auto"
                },
                "inspect": false
              },
              "mappings": [],
              "thresholds": {
                "mode": "absolute",
                "steps": [
                  {
                    "color": "green"
                  },
                  {
                    "color": "red",
                    "value": 80
                  }
                ]
              },
              "unit": "mbytes"
            },
            "overrides": []
          },
          "gridPos": {
            "h": 11,
            "w": 9,
            "x": 15,
            "y": 55
          },
          "id": 10,
          "options": {
            "cellHeight": "sm",
            "footer": {
              "countRows": false,
              "fields": "",
              "reducer": [
                "sum"
              ],
              "show": false
            },
            "showHeader": true
          },
          "pluginVersion": "11.1.4",
          "targets": [
            {
              "datasource": {
                "type": "prometheus",
                "uid": "${DS_PROMETHEUS}"
              },
              "editorMode": "code",
              "exemplar": false,
              "expr": "gpu_nvidia_memory_total{exported_job=\"$gpu_nvidia\"}",
              "format": "table",
              "instant": true,
              "interval": "",
              "legendFormat": "__auto",
              "range": false,
              "refId": "A"
            }
          ],
          "title": "GPU MEM总量",
          "transformations": [
            {
              "id": "filterFieldsByName",
              "options": {
                "include": {
                  "names": [
                    "instance",
                    "nodename",
                    "Value"
                  ]
                }
              }
            },
            {
              "id": "organize",
              "options": {
                "excludeByName": {},
                "includeByName": {},
                "indexByName": {},
                "renameByName": {
                  "Value": "MEM总量"
                }
              }
            }
          ],
          "type": "table"
        },
        {
          "datasource": {
            "type": "prometheus",
            "uid": "${datasource}"
          },
          "description": "",
          "fieldConfig": {
            "defaults": {
              "color": {
                "mode": "palette-classic"
              },
              "custom": {
                "axisBorderShow": false,
                "axisCenteredZero": false,
                "axisColorMode": "text",
                "axisLabel": "",
                "axisPlacement": "auto",
                "barAlignment": 0,
                "drawStyle": "line",
                "fillOpacity": 0,
                "gradientMode": "none",
                "hideFrom": {
                  "legend": false,
                  "tooltip": false,
                  "viz": false
                },
                "insertNulls": false,
                "lineInterpolation": "linear",
                "lineWidth": 1,
                "pointSize": 5,
                "scaleDistribution": {
                  "type": "linear"
                },
                "showPoints": "auto",
                "spanNulls": false,
                "stacking": {
                  "group": "A",
                  "mode": "none"
                },
                "thresholdsStyle": {
                  "mode": "off"
                }
              },
              "mappings": [],
              "thresholds": {
                "mode": "absolute",
                "steps": [
                  {
                    "color": "green"
                  },
                  {
                    "color": "red",
                    "value": 80
                  }
                ]
              },
              "unit": "watt"
            },
            "overrides": []
          },
          "gridPos": {
            "h": 11,
            "w": 15,
            "x": 0,
            "y": 66
          },
          "id": 11,
          "options": {
            "legend": {
              "calcs": [
                "max",
                "mean",
                "lastNotNull"
              ],
              "displayMode": "table",
              "placement": "right",
              "showLegend": true
            },
            "tooltip": {
              "mode": "single",
              "sort": "none"
            }
          },
          "targets": [
            {
              "datasource": {
                "type": "prometheus",
                "uid": "${DS_PROMETHEUS}"
              },
              "editorMode": "code",
              "expr": "gpu_nvidia_power_usage",
              "instant": false,
              "legendFormat": "{{instance}}",
              "range": true,
              "refId": "A"
            }
          ],
          "title": "功耗",
          "type": "timeseries"
        },
        {
          "datasource": {
            "type": "prometheus",
            "uid": "${datasource}"
          },
          "fieldConfig": {
            "defaults": {
              "color": {
                "mode": "thresholds"
              },
              "custom": {
                "align": "left",
                "cellOptions": {
                  "type": "auto"
                },
                "inspect": false
              },
              "mappings": [],
              "thresholds": {
                "mode": "absolute",
                "steps": [
                  {
                    "color": "green"
                  },
                  {
                    "color": "red",
                    "value": 80
                  }
                ]
              },
              "unit": "watt"
            },
            "overrides": []
          },
          "gridPos": {
            "h": 11,
            "w": 9,
            "x": 15,
            "y": 66
          },
          "id": 12,
          "options": {
            "cellHeight": "sm",
            "footer": {
              "countRows": false,
              "fields": "",
              "reducer": [
                "sum"
              ],
              "show": false
            },
            "showHeader": true
          },
          "pluginVersion": "11.1.4",
          "targets": [
            {
              "datasource": {
                "type": "prometheus",
                "uid": "${DS_PROMETHEUS}"
              },
              "editorMode": "code",
              "exemplar": false,
              "expr": "gpu_nvidia_power_cap",
              "format": "table",
              "instant": true,
              "interval": "",
              "legendFormat": "__auto",
              "range": false,
              "refId": "A"
            }
          ],
          "title": "GPU 功率最大值",
          "transformations": [
            {
              "id": "filterFieldsByName",
              "options": {
                "include": {
                  "names": [
                    "instance",
                    "nodename",
                    "Value"
                  ]
                }
              }
            },
            {
              "id": "organize",
              "options": {
                "excludeByName": {},
                "includeByName": {},
                "indexByName": {},
                "renameByName": {
                  "Value": "最大功率"
                }
              }
            }
          ],
          "type": "table"
        }
      ],
      "repeat": "datasource",
      "repeatDirection": "h",
      "title": "GPU",
      "type": "row"
    },
    {
      "collapsed": true,
      "gridPos": {
        "h": 1,
        "w": 24,
        "x": 0,
        "y": 42
      },
      "id": 13,
      "panels": [
        {
          "datasource": {
            "type": "prometheus",
            "uid": "${datasource}"
          },
          "fieldConfig": {
            "defaults": {
              "color": {
                "mode": "palette-classic"
              },
              "custom": {
                "axisBorderShow": false,
                "axisCenteredZero": false,
                "axisColorMode": "text",
                "axisLabel": "",
                "axisPlacement": "auto",
                "barAlignment": 0,
                "drawStyle": "line",
                "fillOpacity": 0,
                "gradientMode": "none",
                "hideFrom": {
                  "legend": false,
                  "tooltip": false,
                  "viz": false
                },
                "insertNulls": false,
                "lineInterpolation": "linear",
                "lineWidth": 1,
                "pointSize": 5,
                "scaleDistribution": {
                  "type": "linear"
                },
                "showPoints": "auto",
                "spanNulls": false,
                "stacking": {
                  "group": "A",
                  "mode": "none"
                },
                "thresholdsStyle": {
                  "mode": "off"
                }
              },
              "mappings": [],
              "thresholds": {
                "mode": "absolute",
                "steps": [
                  {
                    "color": "green"
                  },
                  {
                    "color": "red",
                    "value": 80
                  }
                ]
              },
              "unit": "bytes"
            },
            "overrides": []
          },
          "gridPos": {
            "h": 12,
            "w": 24,
            "x": 0,
            "y": 43
          },
          "id": 14,
          "options": {
            "legend": {
              "calcs": [
                "max",
                "mean",
                "lastNotNull"
              ],
              "displayMode": "table",
              "placement": "right",
              "showLegend": true,
              "sortBy": "Mean",
              "sortDesc": true
            },
            "tooltip": {
              "mode": "single",
              "sort": "none"
            }
          },
          "targets": [
            {
              "datasource": {
                "type": "prometheus",
                "uid": "${DS_PROMETHEUS}"
              },
              "editorMode": "code",
              "expr": "sum(irate(node_network_receive_bytes_total{job=\"$job\"}[$__rate_interval]) + irate(node_network_transmit_bytes_total{job=\"$job\"}[$__rate_interval])) by(instance)",
              "hide": false,
              "instant": false,
              "legendFormat": "__auto",
              "range": true,
              "refId": "A"
            },
            {
              "datasource": {
                "type": "prometheus",
                "uid": "${datasource}"
              },
              "editorMode": "code",
              "expr": "sum(irate(node_network_receive_bytes_total[$__rate_interval]))by(device, instance)",
              "hide": true,
              "instant": false,
              "legendFormat": "{{instance}} {{device}}",
              "range": true,
              "refId": "B"
            }
          ],
          "title": "网络速率",
          "type": "timeseries"
        },
        {
          "datasource": {
            "type": "prometheus",
            "uid": "${DS_PROMETHEUS}"
          },
          "fieldConfig": {
            "defaults": {
              "color": {
                "mode": "palette-classic"
              },
              "custom": {
                "axisBorderShow": false,
                "axisCenteredZero": false,
                "axisColorMode": "text",
                "axisLabel": "",
                "axisPlacement": "auto",
                "barAlignment": 0,
                "drawStyle": "line",
                "fillOpacity": 0,
                "gradientMode": "none",
                "hideFrom": {
                  "legend": false,
                  "tooltip": false,
                  "viz": false
                },
                "insertNulls": false,
                "lineInterpolation": "linear",
                "lineWidth": 1,
                "pointSize": 5,
                "scaleDistribution": {
                  "type": "linear"
                },
                "showPoints": "auto",
                "spanNulls": false,
                "stacking": {
                  "group": "A",
                  "mode": "none"
                },
                "thresholdsStyle": {
                  "mode": "off"
                }
              },
              "mappings": [],
              "thresholds": {
                "mode": "absolute",
                "steps": [
                  {
                    "color": "green"
                  },
                  {
                    "color": "red",
                    "value": 80
                  }
                ]
              },
              "unit": "bytes"
            },
            "overrides": []
          },
          "gridPos": {
            "h": 12,
            "w": 24,
            "x": 0,
            "y": 55
          },
          "id": 15,
          "options": {
            "legend": {
              "calcs": [
                "max",
                "mean",
                "lastNotNull"
              ],
              "displayMode": "table",
              "placement": "right",
              "showLegend": true
            },
            "tooltip": {
              "mode": "single",
              "sort": "none"
            }
          },
          "targets": [
            {
              "datasource": {
                "type": "prometheus",
                "uid": "${datasource}"
              },
              "editorMode": "code",
              "expr": "sum(node_network_receive_bytes_total{job=\"$job\"} + node_network_transmit_bytes_total{job=\"$job\"}) by(instance)",
              "instant": false,
              "legendFormat": "__auto",
              "range": true,
              "refId": "A"
            }
          ],
          "title": "流量使用量",
          "type": "timeseries"
        }
      ],
      "title": "网络/IO",
      "type": "row"
    },
    {
      "collapsed": true,
      "gridPos": {
        "h": 1,
        "w": 24,
        "x": 0,
        "y": 43
      },
      "id": 16,
      "panels": [
        {
          "datasource": {
            "type": "prometheus",
            "uid": "${DS_PROMETHEUS}"
          },
          "fieldConfig": {
            "defaults": {
              "color": {
                "mode": "palette-classic"
              },
              "custom": {
                "axisBorderShow": false,
                "axisCenteredZero": false,
                "axisColorMode": "text",
                "axisLabel": "",
                "axisPlacement": "auto",
                "barAlignment": 0,
                "drawStyle": "line",
                "fillOpacity": 0,
                "gradientMode": "none",
                "hideFrom": {
                  "legend": false,
                  "tooltip": false,
                  "viz": false
                },
                "insertNulls": false,
                "lineInterpolation": "linear",
                "lineWidth": 1,
                "pointSize": 5,
                "scaleDistribution": {
                  "type": "linear"
                },
                "showPoints": "auto",
                "spanNulls": false,
                "stacking": {
                  "group": "A",
                  "mode": "none"
                },
                "thresholdsStyle": {
                  "mode": "off"
                }
              },
              "mappings": [],
              "thresholds": {
                "mode": "absolute",
                "steps": [
                  {
                    "color": "green"
                  },
                  {
                    "color": "red",
                    "value": 80
                  }
                ]
              },
              "unit": "bytes"
            },
            "overrides": []
          },
          "gridPos": {
            "h": 13,
            "w": 24,
            "x": 0,
            "y": 68
          },
          "id": 17,
          "options": {
            "legend": {
              "calcs": [
                "max",
                "mean",
                "lastNotNull"
              ],
              "displayMode": "table",
              "placement": "right",
              "showLegend": true
            },
            "tooltip": {
              "mode": "single",
              "sort": "none"
            }
          },
          "targets": [
            {
              "datasource": {
                "type": "prometheus",
                "uid": "${DS_PROMETHEUS}"
              },
              "editorMode": "code",
              "expr": "sum(irate(node_disk_read_time_seconds_total[$__rate_interval]) + irate(node_disk_write_time_seconds_total[$__rate_interval]))by(instance)",
              "instant": false,
              "legendFormat": "__auto",
              "range": true,
              "refId": "A"
            }
          ],
          "title": "硬盘IO",
          "type": "timeseries"
        }
      ],
      "repeat": "datasource",
      "repeatDirection": "h",
      "title": "硬盘IO",
      "type": "row"
    },
    {
      "collapsed": true,
      "gridPos": {
        "h": 1,
        "w": 24,
        "x": 0,
        "y": 44
      },
      "id": 18,
      "panels": [
        {
          "datasource": {
            "type": "prometheus",
            "uid": "${datasource}"
          },
          "fieldConfig": {
            "defaults": {
              "color": {
                "mode": "thresholds"
              },
              "custom": {
                "align": "auto",
                "cellOptions": {
                  "type": "auto"
                },
                "inspect": false
              },
              "mappings": [],
              "thresholds": {
                "mode": "absolute",
                "steps": [
                  {
                    "color": "green"
                  },
                  {
                    "color": "red",
                    "value": 80
                  }
                ]
              },
              "unit": "bytes"
            },
            "overrides": [
              {
                "matcher": {
                  "id": "byName",
                  "options": "可用%"
                },
                "properties": [
                  {
                    "id": "unit",
                    "value": "percent"
                  }
                ]
              }
            ]
          },
          "gridPos": {
            "h": 14,
            "w": 24,
            "x": 0,
            "y": 82
          },
          "id": 19,
          "options": {
            "cellHeight": "sm",
            "footer": {
              "countRows": false,
              "fields": "",
              "reducer": [
                "sum"
              ],
              "show": false
            },
            "showHeader": true,
            "sortBy": [
              {
                "desc": true,
                "displayName": "可用%"
              }
            ]
          },
          "pluginVersion": "11.1.4",
          "targets": [
            {
              "datasource": {
                "type": "prometheus",
                "uid": "${DS_PROMETHEUS}"
              },
              "editorMode": "code",
              "exemplar": false,
              "expr": "node_filesystem_size_bytes{job=\"$job\", device=~\"/dev/(sd.*|vd.*|hd.*|nvme.*|mapper/.*)\"}",
              "format": "table",
              "instant": true,
              "interval": "",
              "legendFormat": "__auto",
              "range": false,
              "refId": "A"
            },
            {
              "datasource": {
                "type": "prometheus",
                "uid": "${datasource}"
              },
              "editorMode": "code",
              "exemplar": false,
              "expr": "node_filesystem_avail_bytes{job=\"$job\", device=~\"/dev/(sd.*|vd.*|hd.*|nvme.*|mapper/.*)\"}",
              "format": "table",
              "hide": false,
              "instant": true,
              "interval": "",
              "legendFormat": "__auto",
              "range": false,
              "refId": "B"
            },
            {
              "datasource": {
                "type": "prometheus",
                "uid": "${DS_PROMETHEUS}"
              },
              "editorMode": "code",
              "exemplar": false,
              "expr": "(1 - (node_filesystem_avail_bytes{job=\"$job\", device=~\"/dev/(sd.*|vd.*|hd.*|nvme.*|mapper/.*)\"} / node_filesystem_size_bytes{job=\"$job\", device=~\"/dev/(sd.*|vd.*|hd.*|nvme.*|mapper/.*)\"}))*100",
              "format": "table",
              "hide": false,
              "instant": true,
              "legendFormat": "__auto",
              "range": false,
              "refId": "C"
            },
            {
              "datasource": {
                "type": "prometheus",
                "uid": "${datasource}"
              },
              "editorMode": "code",
              "exemplar": false,
              "expr": "node_uname_info",
              "format": "table",
              "hide": false,
              "instant": true,
              "interval": "",
              "legendFormat": "__auto",
              "range": false,
              "refId": "D"
            }
          ],
          "title": "磁盘使用情况",
          "transformations": [
            {
              "id": "filterFieldsByName",
              "options": {
                "include": {
                  "names": [
                    "Time",
                    "device",
                    "fstype",
                    "instance",
                    "mountpoint",
                    "Value #A",
                    "Value #B",
                    "Value #C",
                    "nodename"
                  ]
                }
              }
            },
            {
              "id": "merge",
              "options": {}
            },
            {
              "id": "organize",
              "options": {
                "excludeByName": {},
                "includeByName": {},
                "indexByName": {
                  "Time": 0,
                  "Value #A": 6,
                  "Value #B": 7,
                  "Value #C": 8,
                  "Value #D": 9,
                  "device": 4,
                  "fstype": 5,
                  "instance": 2,
                  "mountpoint": 3,
                  "nodename": 1
                },
                "renameByName": {
                  "Value #A": "大小",
                  "Value #B": "可用",
                  "Value #C": "可用%",
                  "Value #D": "",
                  "nodename": "hostname"
                }
              }
            }
          ],
          "type": "table"
        }
      ],
      "title": "硬盘使用情况",
      "type": "row"
    }
  ],
  "refresh": "10s",
  "schemaVersion": 39,
  "tags": [
    "zx"
  ],
  "templating": {
    "list": [
      {
        "current": {},
        "description": "prometheus源",
        "hide": 2,
        "includeAll": false,
        "label": "数据来源",
        "multi": false,
        "name": "datasource",
        "options": [],
        "query": "prometheus",
        "refresh": 1,
        "regex": "",
        "skipUrlSync": false,
        "type": "datasource"
      },
      {
        "current": {},
        "datasource": {
          "type": "prometheus",
          "uid": "${DS_PROMETHEUS}"
        },
        "definition": "label_values(node_uname_info{job=\"node\"},job)",
        "hide": 2,
        "includeAll": false,
        "label": "job类型",
        "multi": false,
        "name": "job",
        "options": [],
        "query": {
          "qryType": 1,
          "query": "label_values(node_uname_info{job=\"node\"},job)",
          "refId": "PrometheusVariableQueryEditor-VariableQuery"
        },
        "refresh": 1,
        "regex": "",
        "skipUrlSync": false,
        "sort": 0,
        "type": "query"
      },
      {
        "current": {},
        "datasource": {
          "type": "prometheus",
          "uid": "${datasource}"
        },
        "definition": "label_values({exported_job=\"gpu_nvidia\"},exported_job)",
        "hide": 2,
        "includeAll": false,
        "label": "pushgateway数据",
        "multi": true,
        "name": "gpu_nvidia",
        "options": [],
        "query": {
          "qryType": 1,
          "query": "label_values({exported_job=\"gpu_nvidia\"},exported_job)",
          "refId": "PrometheusVariableQueryEditor-VariableQuery"
        },
        "refresh": 1,
        "regex": "",
        "skipUrlSync": false,
        "sort": 0,
        "type": "query"
      }
    ]
  },
  "time": {
    "from": "now-1h",
    "to": "now"
  },
  "timepicker": {},
  "timezone": "browser",
  "title": "多机器聚合监控-v11",
  "uid": "cduzwz7nqfldse",
  "version": 15,
  "weekStart": ""
}